{"era": "fhvhv_2019", "period": "PM_PEAK", "k": 20, "centroids": [{"cluster_id": 0, "centroid_lat": 40.715277139405195, "centroid_lon": -74.00190553521199, "trip_count": 833627}, {"cluster_id": 1, "centroid_lat": 40.83199500399072, "centroid_lon": -73.9246831270056, "trip_count": 702384}, {"cluster_id": 2, "centroid_lat": 40.60903486705814, "centroid_lon": -73.96164209008917, "trip_count": 294752}, {"cluster_id": 3, "centroid_lat": 40.76090930747441, "centroid_lon": -73.97601983543137, "trip_count": 1527246}, {"cluster_id": 4, "centroid_lat": 40.654108710399, "centroid_lon": -73.78498146143541, "trip_count": 256631}, {"cluster_id": 5, "centroid_lat": 40.68248660139934, "centroid_lon": -73.93485698514948, "trip_count": 618870}, {"cluster_id": 6, "centroid_lat": 40.636401112093864, "centroid_lon": -73.92124720388762, "trip_count": 245835}, {"cluster_id": 7, "centroid_lat": 40.68311789284105, "centroid_lon": -73.98196345325582, "trip_count": 614381}, {"cluster_id": 8, "centroid_lat": 40.71254228209133, "centroid_lon": -73.78073902101802, "trip_count": 230070}, {"cluster_id": 9, "centroid_lat": 40.725842414327964, "centroid_lon": -73.947597461039, "trip_count": 509595}, {"cluster_id": 10, "centroid_lat": 40.76439124423661, "centroid_lon": -73.8090968062381, "trip_count": 139307}, {"cluster_id": 11, "centroid_lat": 40.63133953045211, "centroid_lon": -74.00480717427656, "trip_count": 242676}, {"cluster_id": 12, "centroid_lat": 40.87430647195504, "centroid_lon": -73.88747965948019, "trip_count": 395396}, {"cluster_id": 13, "centroid_lat": 40.66720955541957, "centroid_lon": -73.8818465117543, "trip_count": 246563}, {"cluster_id": 14, "centroid_lat": 40.73983670638026, "centroid_lon": -73.9927417432172, "trip_count": 1419757}, {"cluster_id": 15, "centroid_lat": 40.72070917441066, "centroid_lon": -73.8691612190576, "trip_count": 332436}, {"cluster_id": 16, "centroid_lat": 40.79032481216943, "centroid_lon": -73.95644573203705, "trip_count": 766779}, {"cluster_id": 17, "centroid_lat": 40.83952055461036, "centroid_lon": -73.85763932666264, "trip_count": 361571}, {"cluster_id": 18, "centroid_lat": 40.765123881172656, "centroid_lon": -73.88873219113796, "trip_count": 436588}, {"cluster_id": 19, "centroid_lat": 40.602895819847106, "centroid_lon": -74.12831745004897, "trip_count": 103513}]}